<odoo>
    <record id="invoice_paper_format_A5" model="report.paperformat">
        <field name="name">Invoice A5</field>
        <field name="default" eval="True" />
        <field name="format">A5</field>
        <field name="orientation">Portrait</field>
        <field name="margin_top">20</field>
        <field name="margin_bottom">10</field>
        <field name="margin_left">7</field>
        <field name="margin_right">7</field>
        <field name="header_line" eval="False" />
        <field name="header_spacing">15</field>
        <field name="dpi">90</field>
    </record>

    <report
        id="action_report_saleorder_A5"
        string="Quotation / Order A5"
        model="sale.order"
        report_type="qweb-pdf"
        file="report_customization.report_saleorder_A5"
        name="report_customization.report_saleorder_A5"
        print_report_name="(object.state in ('draft', 'sent') and 'Quotation - %s' % (object.name)) or 'Order - %s' % (object.name)"
        paperformat="report_customization.invoice_paper_format_A5"
    />

    <report
            id="sale.action_report_saleorder"
            string="Quotation / Order A4"
            model="sale.order"
            report_type="qweb-pdf"
            file="sale.report_saleorder"
            name="sale.report_saleorder"
            print_report_name="(object.state in ('draft', 'sent') and 'Quotation - %s' % (object.name)) or 'Order - %s' % (object.name)"
        />

    <template id="report_saleorder_A5">
        <t t-call="web.html_container">
            <t t-foreach="docs" t-as="doc">
                <t t-call="report_customization.report_saleorder_document_A5" t-lang="doc.partner_id.lang"/>
            </t>
        </t>
    </template>

    <template id="sale_report_external_layout_standard_A5">
        <div t-attf-class="header o_company_#{company.id}_layout">
            <div class="row" style="width: 100%; font-size: 11px; color: black;" >
                <div class=" " style="width: 27%; margin-right: 15px;">
                    <img t-if="company.invoice_logo" t-att-src="image_data_uri(company.invoice_logo)" style="max-width: 150px; max-height: 35px;" alt="Logo"/>
                    <img t-elif="company.logo" t-att-src="image_data_uri(company.logo)" style="max-width: 150px; max-height: 35px;" alt="Logo"/>
                </div>
                <div class="" style="width: 30%; margin-right: 2%;">
                    <div style="color: #1D54A6;" t-if="company.phone" class="">
                        <i class="fa fa-phone" style="margin-right: 5px;" ></i><span t-field="company.phone"/>
                    </div>
                    <div style="color: #1D54A6;" t-if="company.email" class="">
                        <i class="fa fa-envelope" style="margin-right: 5px;" /><span t-field="company.email"/>
                    </div>
                </div>
                <div class="" style="width: 40%;">
                    <div style="color: #1D54A6;" t-if="company.website" class="">
                        <i class="fa fa-globe" style="margin-right: 5px;" /><span t-field="company.website"/>
                    </div>
                    <div style="color: #1D54A6;" t-if="company.website" class="">
                            <i class="fa fa-facebook-square" style="margin-right: 5px;" />
                        <span>https://www.facebook.com/LIVEPlaza</span>
                    </div>
                </div>
<!--                <div class="col-5 text-right" style="margin-top:22px;" t-esc="company.phone" name="moto"/>-->
<!--                <div class="col-9 text-right" style="margin-top:22px;" t-esc="company.email" name="moto"/>-->
            </div>
            <div class="row" style="height: 12px; width: 100%; background: #DAE4F1; margin-top: 20px;"></div>
        </div>
        <div t-attf-class="article o_report_layout_standard o_company_#{company.id}_layout"  t-att-data-oe-model="o and o._name"
             t-att-data-oe-id="o and o.id" t-att-data-oe-lang="o and o.env.context.get('lang')" >
            <t t-call="report_customization.sale_report_address_layout"/>
            <t t-raw="0"/>
        </div>
        <div t-attf-class="o_company_#{company.id}_layout">
            <div style="height: 300px; width: 100%; background: black"></div>
        </div>
        <div t-attf-class="footer o_standard_footer o_company_#{company.id}_layout">
                <div class="text-center" style="border-top: 1px solid black;">
<!--                <ul class="list-inline mb4">-->
<!--                    &lt;!&ndash; using the list-inline-item class from bootstrap causes weird behaviours in pdf report-->
<!--                         adding d-inline class fixes the problem&ndash;&gt;-->
<!--                    <li t-if="company.phone" class="list-inline-item d-inline">Phone: <span t-field="company.phone"/></li>-->
<!--                    <li t-if="company.email" class="list-inline-item d-inline">Email: <span t-field="company.email"/></li>-->
<!--                    <li t-if="company.website" class="list-inline-item d-inline">Web: <span t-field="company.website"/></li>-->
<!--                    <li t-if="company.vat" class="list-inline-item d-inline"><t t-esc="company.country_id.vat_label or 'Tax ID'"/>: <span t-field="company.vat"/></li>-->
<!--                </ul>-->
<!--                <div name="financial_infos">-->
<!--                    <span t-field="company.report_footer"/>-->
<!--                </div>-->
                <div t-if="report_type == 'pdf'" class="text-muted">
                    Page: <span class="page"/> / <span class="topage"/>
                </div>
            </div>
        </div>
    </template>

    <template id="sale_report_external_layout_A5">
        <t t-if="not o" t-set="o" t-value="doc"/>
        <t t-if="not company">
            <!-- Multicompany -->
            <t t-if="company_id">
                <t t-set="company" t-value="company_id"/>
            </t>
            <t t-elif="o and 'company_id' in o">
                <t t-set="company" t-value="o.company_id.sudo()"/>
            </t>
            <t t-else="else">
                <t t-set="company" t-value="res_company"/>
            </t>
        </t>
        <t t-call="report_customization.sale_report_external_layout_standard_A5"><t t-raw="0"/> </t>
<!--        <t t-if="company.external_report_layout_id" t-call="{{company.external_report_layout_id.key}}"><t t-raw="0"/></t>-->
<!--        <t t-else="else" t-call="report_customization.sale_report_external_layout_standard"><t t-raw="0"/></t>-->
    </template>

    <template id="report_saleorder_document_A5">
        <t t-call="report_customization.sale_report_external_layout_A5">
            <t t-set="doc" t-value="doc.with_context(lang=doc.partner_id.lang)" />
            <t t-set="company" t-value="doc.company_id" />
            <div class="sale_report_template" style="font-size: 12px;">
                <t t-set="payment_tx_id" t-value="doc.get_portal_last_transaction()"/>
                <t t-set="carrier" t-value="request.env['delivery.carrier'].sudo().search([('id', '=', doc.selected_carrier_id)])"/>
                <t t-set="count" t-value="0" />
                <t t-set="number" t-value="0" />
                <t t-set="line_in_page" t-value="5" />
                <t t-set="sol_total_list" t-value="doc._compute_sol_page_break(line_in_page)" />
                <t t-set="picking" t-value="request.env['stock.picking'].sudo().search([('origin', '=', doc.name)])" />
                <t t-set="vendor" t-value="''"/>
                <t t-foreach="picking" t-as="p">
                    <t t-if="p.picking_type_id.name == 'Delivery Orders'">
                        <t t-set="vendor" t-value="p.vendor_id"/>
                    </t>
                </t>
                <t t-foreach="sol_total_list" t-as="sol_list">
                    <div style="height: 600px">
                        <div class="customer_info_container clearfix" style="font-size: 11px;">
                            <table class="cart_modal_table" style="width: 100%;">
                                <tbody>
                                    <tr>
                                        <td class="summary_td_style">Customer</td>
                                        <td class="text-right">:</td>
                                        <td class="summary_td_style"  style="width: 38%;"><t t-esc="doc.partner_id.name"/></td>
                                        <td class="summary_td_style">Sale Order No</td>
                                        <td class="text-right">:</td>
                                        <td class="summary_td_style"><t t-esc="doc.name"/></td>
                                    </tr>
                                    <tr>
                                        <td class="summary_td_style">Phone</td>
                                        <td class="text-right">:</td>
                                        <td class="summary_td_style"><t t-esc="doc.partner_id.phone"/></td>
                                        <td class="summary_td_style">Order Date</td>
                                        <td class="text-right">:</td>
                                        <td class="summary_td_style"><t t-esc="doc.date_order.strftime('%d %b %Y')"/></td>
                                    </tr>
                                    <tr>
                                        <td class="summary_td_style">Address</td>
                                        <td class="text-right">:</td>
                                        <td class="summary_td_style" style="width: 35%;">
                                            <span t-esc='doc.partner_shipping_id' t-options="dict(widget='contact', fields=['address'],
                                                      no_marker=True, separator=', ')"  class="address-inline"/>
                                        </td>
                                        <td class="summary_td_style">Payment Method</td>
                                        <td class="text-right">:</td>
                                        <td class="summary_td_style"><t t-esc="payment_tx_id.acquirer_id.name"/></td>
                                    </tr>
                                    <tr>
                                        <td class="summary_td_style">Township</td>
                                        <td class="text-right">:</td>
                                        <td class="summary_td_style"><t t-esc="doc.partner_shipping_id.township_id.name"/></td>
                                        <td class="summary_td_style">Shipping Method</td>
                                        <td class="text-right">:</td>
                                        <td class="summary_td_style" >
                                            <t t-if="carrier.shipping_method" t-esc="carrier.shipping_method"/>
                                            <t t-else="">Standard</t>
                                        </td>
                                    </tr>
                                    <tr>
                                        <td class="summary_td_style">State</td>
                                        <td class="text-right">:</td>
                                        <td class="summary_td_style"><t t-esc="doc.partner_shipping_id.state_id.name"/></td>
                                        <td class="summary_td_style">Shipping Service Provider</td>
                                        <td class="text-right">:</td>
                                        <td class="summary_td_style">
                                            <t t-if="vendor" t-esc="vendor.name"/>
                                            <t t-else=""></t>
                                        </td>
                                    </tr>
                                </tbody>
                            </table>
                        </div>
                        <div class="sale_report_order" style="margin-top: 20px;">
                            <t t-set="display_discount" t-value="any([l.discount or l.discount_amount for l in doc.order_line])"/>
                            <t t-set="sol_count" t-value="len(doc.order_line)" />
                            <table class="sale_report_table" style="">
                                <tr>
                                    <td class="th_style">No.</td>
                                    <td class="th_style" t-att-style="'width: 30%;' if display_discount else 'width: 35%;'">Description</td>
                                    <td class="th_style">Shop Code</td>
                                    <td class="th_style">Unit Price</td>
                                    <td class="th_style">Quantity</td>
                                    <td t-if="display_discount" class="th_style">Discount</td>
                                    <td class="th_style">Amount</td>
                                </tr>
                                <tbody>
                                    <t t-foreach="sol_list" t-as="line">
                                        <tr t-att-class="'bg-200 font-weight-bold o_line_section' if line.display_type == 'line_section' else 'font-italic o_line_note' if line.display_type == 'line_note' else ''"
                                         t-if="(not line.is_delivery) and ( line.delivery_status != 'cancel') and (not line.is_voucher)">
                                            <t t-set="number" t-value="number + 1" />
                                            <t t-if="not line.display_type">
                                                <td class="text-center td_style"><span style="color: black;" t-esc="number" /></td>
                                                <td class="td_style" ><span t-field="line.product_id"/></td>
                                                <td class="td_style"><span t-field="line.product_id.shop_code"/> </td>
                                                <td class="text-right td_style">
                                                     <span t-field="line.price_unit"/>
                                                </td>
                                                <td class="text-right td_style">
                                                    <span t-field="line.product_uom_qty"/>
                                                    <span t-field="line.product_uom" groups="uom.group_uom"/>
                                                </td>
                                                <td t-if="display_discount" class="text-right td_style" >
                                                    <span t-if="line.discount_amount"> <t t-esc="line.discount_amount"/> Ks</span>
                                                    <span t-else="" ><t t-esc="line.discount"/> % </span>
                                                </td>
                                                <td class="text-right o_price_total td_style">
                                                    <span t-field="line.price_subtotal" groups="account.group_show_line_subtotals_tax_excluded"/>
                                                    <span t-field="line.price_total" groups="account.group_show_line_subtotals_tax_included"/>
                                                </td>
                                            </t>
                                        </tr>
                                    </t>
                                    </tbody>
                            </table>
                            <t t-set="count" t-value="count + 1" />
                            <t t-if="count &lt; len(sol_total_list)">
                                <p style="page-break-after: always;"/>
                            </t>
                            <t t-else="">
                                <div style="margin-top: 10px;">
                                    <table style="width: 100%;">
                                        <tr>
                                            <td class="text-center" style="width: 55%; position: relative;">
<!--                                                    <p style="color: #1D54A6; font-size; 15px;">-->
<!--                                                    ဝယ်ယူအားပေးမှုအတွက် အထူးကျေးဇူးတင်ပါသည်။ <br></br>-->
<!--                                                    ကောင်းသောနေ့လေး ဖြစ်ပါစေ။-->
<!--                                                    </p>-->
                                                <img t-if="company.thank_msg_img" t-att-src="image_data_uri(company.thank_msg_img)" style=" width: 80%; position: absolute; bottom: 0; left: 10%;" />
                                                <img t-else="" src="report_customization/static/src/img/thank_msg.png" alt="Thank you for your order"
                                                    style=" width: 80%; position: absolute; bottom: 0; left: 10%;" />
                                            </td>
                                            <td style="width: 45%;">
                                                <t t-set="subtotal" t-value="doc.amount_untaxed - doc.amount_delivery + doc.wk_coupon_value" />
                                                <table class="summary_table">
                                                    <tr>
                                                        <td class="summary_td_style text-right"><strong class="summary">Sub Total</strong></td>
                                                        <td class="summary_td_style text-right">
                                                            <h6 class="summary">
                                                                <strong class="text-right o_price_total">
                                                                    <strong t-esc="subtotal" class="summary monetary_field" style="white-space: nowrap;"
                                                                            t-options='{"widget": "monetary", "display_currency": doc.currency_id,}'/>
                                                                </strong>
                                                            </h6>
                                                        </td>
                                                    </tr>
                                                    <tr t-if="doc.wk_coupon_value">
                                                        <td class="summary_td_style text-right"><h6 class="summary"><strong>Gift Voucher</strong></h6></td>
                                                        <td class="summary_td_style text-right">
                                                            <h6 class="summary">
                                                                <strong class="text-right">
                                                                    <strong t-esc="doc.wk_coupon_value * (-1)" class="summary monetary_field" style="white-space: nowrap;"
                                                                            t-options='{"widget": "monetary", "display_currency": doc.currency_id,}'/>
                                                                </strong>
                                                            </h6>
                                                        </td>
                                                    </tr>
                                                    <tr>
                                                        <td class="summary_td_style text-right">
                                                            <strong t-if="doc.amount_delivery"  class="summary">Delivery Fee</strong>
                                                        </td>
                                                        <td class="summary_td_style text-right">
                                                            <strong t-if="doc.amount_delivery" t-field="doc.amount_delivery" class="summary monetary_field"
                                                                style="white-space: nowrap;" t-options='{"widget": "monetary", "display_currency": doc.currency_id,}'/>
                                                        </td>
                                                    </tr>
                                                    <tr>
                                                        <td class=" text-right bg-blue"><strong class="summary">GRAND TOTAL</strong></td>
                                                        <td class=" text-right bg-blue">
                                                            <strong name="td_subtotal" class="text-right o_price_total summary">
                                                                <span t-field="doc.amount_total" groups="account.group_show_line_subtotals_tax_excluded"/>
                                                            </strong>
                                                        </td>
                                                    </tr>
                                                </table>
                                            </td>
                                        </tr>
                                    </table>
                                </div>
                            </t>
                        </div>
                    </div>
                    <div t-if="company" style="width: 100%; padding-top: 10px; height: 185px;">
                        <t t-if="company.invoice_format == 'plain'">
                            <div class="text-center" >
                                <div t-if="company.image_invoice_1" class="" style="height: 170px;">
                                    <span t-field="company.image_invoice_1" class="img_outer_style"
                                  t-options="{'widget': 'image', 'qweb_img_responsive': False, 'class': 'text-center img_plain_style'}" />
                                </div>
                            </div>
                        </t>
                        <t t-elif="company.invoice_format == 'two_horizontal'">
                            <div class="row" style="width: 100%;  ">
                                <div style="width: 50%; height: 180px;" >
                                    <div t-if="company.image_invoice_1" class="img_outer_style">
                                        <span t-field="company.image_invoice_1" style="width: fit-content; height: 170px;"
                                      t-options="{'widget': 'image', 'qweb_img_responsive': False, 'class': 'img_2hor_style'}" />
                                    </div>
                                </div>
                                <div style="width: 50%; height: 180px; ">
                                    <div t-if="company.image_invoice_2" class="img_outer_style">
                                        <span t-field="company.image_invoice_2" style="width: fit-content; height: 170px;"
                                      t-options="{'widget': 'image', 'qweb_img_responsive': False, 'class': 'img_2hor_style'}" />
                                    </div>
                                </div>
                            </div>
                        </t>
                        <t t-elif="company.invoice_format == 'two_vertical'">
                            <div style="width: 100%; height: 85px;" >
                                <div t-if="company.image_invoice_1" class="img_outer_style">
                                    <span t-field="company.image_invoice_1" style="width: fit-content; height: 80px;"
                                  t-options="{'widget': 'image', 'qweb_img_responsive': False, 'class': 'img_2ver_style'}" />
                                    </div>
                            </div>
                            <div style="width: 100%; height: 85px; ">
                                <div t-if="company.image_invoice_3" class="img_outer_style">
                                    <span t-field="company.image_invoice_3" style="width: fit-content; height: 80px;"
                                  t-options="{'widget': 'image', 'qweb_img_responsive': False, 'class': 'img_2ver_style'}" />
                                </div>
                            </div>
                        </t>
                        <t t-elif="company.invoice_format == 'four_square'">
                            <div class="row" style="width: 100%">
                                <div style="width: 50%; height: 180px;" >
                                    <div class="blank_td_style">
                                        <div t-if="company.image_invoice_1" class="img_outer_style">
                                            <span t-field="company.image_invoice_1" style="width: fit-content; max-width: 256px;"
                                          t-options="{'widget': 'image', 'qweb_img_responsive': False, 'class': 'img_style'}" />
                                        </div>
                                    </div>
                                    <div class="blank_td_style">
                                        <div t-if="company.image_invoice_3" class="img_outer_style">
                                            <span t-field="company.image_invoice_3" style="width: fit-content; max-width: 256px;"
                                          t-options="{'widget': 'image', 'qweb_img_responsive': False, 'class': 'img_style'}" />
                                        </div>
                                    </div>
                                </div>
                                <div style="width: 50%; height: 180px;">
                                    <div class="blank_td_style">
                                        <div t-if="company.image_invoice_2" class="img_outer_style">
                                            <span t-field="company.image_invoice_2" style="width: fit-content; max-width: 256px;"
                                          t-options="{'widget': 'image', 'qweb_img_responsive': False, 'class': 'img_style'}" />
                                        </div>
                                    </div>
                                    <div class="blank_td_style">
                                        <div t-if="company.image_invoice_4" class="img_outer_style">
                                            <span t-field="company.image_invoice_4" style="width: fit-content; max-width: 256px;"
                                          t-options="{'widget': 'image', 'qweb_img_responsive': False, 'class': 'img_style'}" />
                                            </div>
                                    </div>
                                </div>
                            </div>
                        </t>
                        <t t-elif="company.invoice_format == 'top1_bot2'">
                            <div style="height: 180px; ">
                                <div style="width: 100%; height: 90px">
                                    <div t-if="company.image_invoice_1" class="img_outer_style">
                                    <span t-field="company.image_invoice_1" style="width: fit-content; height: 80px;"
                                  t-options="{'widget': 'image', 'qweb_img_responsive': False, 'class': 'img_2ver_style'}" />
                                </div>
                                </div>
                                <div class="row" style="width: 100%; height: 90px">
                                    <div style="width: 50%">
                                        <div t-if="company.image_invoice_3" class="img_outer_style">
                                            <span t-field="company.image_invoice_3" style="width: fit-content; height: 80px;"
                                          t-options="{'widget': 'image', 'qweb_img_responsive': False, 'class': 'img_style'}" />
                                        </div>
                                    </div>
                                    <div style="width: 50%">
                                        <div t-if="company.image_invoice_4" class="img_outer_style">
                                            <span t-field="company.image_invoice_4" style="width: fit-content; height: 80px;"
                                                  t-options="{'widget': 'image', 'qweb_img_responsive': False, 'class': 'img_style'}" />
                                        </div>
                                    </div>
                                </div>
                            </div>
                        </t>
                        <t t-elif="company.invoice_format == 'top2_bot1'">
                            <div style="height: 180px; ">
                                <div class="row" style="width: 100%; height: 90px">
                                    <div style="width: 50%">
                                        <div t-if="company.image_invoice_1" class="img_outer_style">
                                            <span t-field="company.image_invoice_1" style="width: fit-content; height: 80px;"
                                          t-options="{'widget': 'image', 'qweb_img_responsive': False, 'class': 'img_style'}" />
                                        </div>
                                    </div>
                                    <div style="width: 50%">
                                        <div t-if="company.image_invoice_2" class="img_outer_style">
                                            <span t-field="company.image_invoice_2" style="width: fit-content; height: 80px;"
                                          t-options="{'widget': 'image', 'qweb_img_responsive': False, 'class': 'img_style'}" />
                                        </div>
                                    </div>
                                    </div>
                                <div style="width: 100%; height: 90px">
                                    <div t-if="company.image_invoice_3" class="img_outer_style">
                                        <span t-field="company.image_invoice_3" style="width: fit-content; height: 80px;"
                                      t-options="{'widget': 'image', 'qweb_img_responsive': False, 'class': 'img_2ver_style'}" />
                                    </div>
                                </div>
                            </div>
                        </t>
                        <t t-elif="company.invoice_format == 'left1_right2'">
                            <div class="row" style="height: 180px; ">
                                <div style="width: 50%; height: 180px; position: relative;">
                                    <div t-if="company.image_invoice_1" class="img_outer_style" style="height: 100%;">
                                        <span t-field="company.image_invoice_1" style="width: fit-content; height: 80px; "
                                      t-options="{'widget': 'image', 'qweb_img_responsive': False, 'class': 'img_2hor_style'}" />
                                    </div>
                                </div>
                                <div style="width: 50%; height: 180px">
                                    <div style="width: 100%; height: 90px;">
                                        <div t-if="company.image_invoice_2" class="img_outer_style">
                                            <span t-field="company.image_invoice_2" style="width: fit-content; height: 80px;"
                                          t-options="{'widget': 'image', 'qweb_img_responsive': False, 'class': 'img_style'}" />
                                        </div>
                                    </div>
                                    <div style="width: 100%; height: 90px;">
                                        <div t-if="company.image_invoice_4" class="img_outer_style">
                                            <span t-field="company.image_invoice_4" style="width: fit-content; height: 80px;"
                                          t-options="{'widget': 'image', 'qweb_img_responsive': False, 'class': 'img_style'}" />
                                        </div>
                                    </div>
                                </div>
                            </div>
                        </t>
                        <t t-elif="company.invoice_format == 'left2_right1'">
                            <div class="row" style="height: 180px; ">
                                <div style="width: 50%; height: 180px">
                                    <div style="width: 100%; height: 90px;">
                                        <div t-if="company.image_invoice_1" class="img_outer_style">
                                            <span t-field="company.image_invoice_1" style="width: fit-content; height: 80px;"
                                                  t-options="{'widget': 'image', 'qweb_img_responsive': False, 'class': 'img_style'}" />
                                        </div>
                                    </div>
                                    <div style="width: 100%; height: 90px;">
                                        <div t-if="company.image_invoice_3" class="img_outer_style">
                                            <span t-field="company.image_invoice_3" style="width: fit-content; height: 80px;"
                                          t-options="{'widget': 'image', 'qweb_img_responsive': False, 'class': 'img_style'}" />
                                        </div>
                                    </div>
                                </div>
                                <div style="width: 50%; height: 180px; position: relative;">
                                    <div t-if="company.image_invoice_2" class="img_outer_style" style="height: 100%;">
                                        <span t-field="company.image_invoice_2" style="width: fit-content; height: 80px; "
                                      t-options="{'widget': 'image', 'qweb_img_responsive': False, 'class': 'img_2hor_style'}" />
                                    </div>
                                </div>
                            </div>
                        </t>
                    </div>
                </t>
            </div>
        </t>
    </template>
</odoo>
